hover/__init__.py
hover/module_config.py
hover/core/__init__.py
hover/core/dataset.py
hover/core/local_config.py
hover/core/neural.py
hover/core/explorer/__init__.py
hover/core/explorer/base.py
hover/core/explorer/feature.py
hover/core/explorer/functionality.py
hover/core/explorer/local_config.py
hover/core/explorer/specialization.py
hover/core/representation/__init__.py
hover/core/representation/local_config.py
hover/core/representation/manifold.py
hover/core/representation/reduction.py
hover/core/representation/trajectory.py
hover/recipes/__init__.py
hover/recipes/experimental.py
hover/recipes/stable.py
hover/recipes/subroutine.py
hover/utils/__init__.py
hover/utils/common_nn.py
hover/utils/datasets.py
hover/utils/metrics.py
hover/utils/misc.py
hover/utils/snorkel_helper.py
hover/utils/torch_helper.py
hover/utils/bokeh_helper/__init__.py
hover/utils/bokeh_helper/local_config.py
hover/utils/meta/__init__.py
hover/utils/meta/traceback.py
hover-0.8.1.dist-info/LICENSE
hover-0.8.1.dist-info/METADATA
hover-0.8.1.dist-info/WHEEL
hover-0.8.1.dist-info/top_level.txt
hover-0.8.1.dist-info/RECORD
