Metadata-Version: 2.1
Name: hover
Version: 0.8.1
Summary: Label data at scale. Fun and precision included.
Home-page: https://github.com/phurwicz/hover
Author: Pavel
Author-email: pavelhurwicz@gmail.com
Classifier: Programming Language :: Python :: 3
Classifier: Development Status :: 4 - Beta
Classifier: License :: OSI Approved :: MIT License
Classifier: Operating System :: OS Independent
Requires-Python: >=3.8
License-File: LICENSE
Requires-Dist: bokeh (>=3.0.3)
Requires-Dist: scikit-learn (>=0.20.0)
Requires-Dist: torch (>=1.10.0)
Requires-Dist: pandas (>=1.3.0)
Requires-Dist: numpy (>=1.22)
Requires-Dist: scipy (>=1.3.2)
Requires-Dist: tqdm (>=4.0)
Requires-Dist: rich (>=11.0.0)
Requires-Dist: deprecated (>=1.1.0)
Requires-Dist: umap-learn (>=0.3.10)
Requires-Dist: flexmod (>=0.1.0)
